pyron_rs-0.2.1.dist-info/METADATA
pyron_rs-0.2.1.dist-info/WHEEL
pyron_rs-0.2.1.dist-info/license_files/LICENSE
pyron_rs/__init__.py
pyron_rs/pyron_rs.cpython-310-x86_64-linux-gnu.so
pyron_rs-0.2.1.dist-info/RECORD
