Metadata-Version: 2.1
Name: pyron-rs
Version: 0.2.1
Classifier: Programming Language :: Rust
Classifier: Programming Language :: Python :: Implementation :: CPython
Classifier: Programming Language :: Python :: Implementation :: PyPy
License-File: LICENSE
Summary: A game development platform that integrates into python
Keywords: python,game
Home-Page: https://github.com/Aurlex/pyron-rs
Requires-Python: >=3.7
Project-URL: Source Code, https://github.com/Aurlex/pyron-rs
